qtbox/__init__.py
qtbox/main.py
qtbox/demo/__init__.py
qtbox/demo/checkbox/__init__.py
qtbox/demo/checkbox/func/__init__.py
qtbox/demo/checkbox/func/demo1.py
qtbox/demo/checkbox/func/demo2.py
qtbox/demo/checkbox/style/__init__.py
qtbox/demo/checkbox/style/demo1.py
qtbox/demo/checkbox/style/demo2.py
qtbox/demo/checkbox/style/demo3.py
qtbox/demo/checkbox/style/demo4.py
qtbox/demo/combobox/__init__.py
qtbox/demo/combobox/func/__init__.py
qtbox/demo/combobox/func/demo1.py
qtbox/demo/combobox/func/demo2.py
qtbox/demo/combobox/style/__init__.py
qtbox/demo/combobox/style/demo1.py
qtbox/demo/combobox/style/demo2.py
qtbox/demo/combobox/style/demo3.py
qtbox/demo/dial/__init__.py
qtbox/demo/dial/func/__init__.py
qtbox/demo/dial/func/demo1.py
qtbox/demo/dial/style/__init__.py
qtbox/demo/dial/style/demo1.py
qtbox/demo/dial/style/demo2.py
qtbox/demo/label/__init__.py
qtbox/demo/label/func/__init__.py
qtbox/demo/label/func/demo1.py
qtbox/demo/label/func/demo2.py
qtbox/demo/label/func/demo3.py
qtbox/demo/label/func/demo4.py
qtbox/demo/label/func/demo5.py
qtbox/demo/label/func/demo6.py
qtbox/demo/label/func/demo7.py
qtbox/demo/label/style/__init__.py
qtbox/demo/label/style/demo1.py
qtbox/demo/label/style/demo2.py
qtbox/demo/label/style/demo3.py
qtbox/demo/label/style/demo4.py
qtbox/demo/lcdnumber/__init__.py
qtbox/demo/lcdnumber/func/__init__.py
qtbox/demo/lcdnumber/func/demo1.py
qtbox/demo/lcdnumber/func/demo2.py
qtbox/demo/lcdnumber/func/demo3.py
qtbox/demo/lcdnumber/style/__init__.py
qtbox/demo/lcdnumber/style/demo1.py
qtbox/demo/lcdnumber/style/demo2.py
qtbox/demo/lcdnumber/style/demo3.py
qtbox/demo/lcdnumber/style/demo4.py
qtbox/demo/lcdnumber/style/demo5.py
qtbox/demo/lineedit/__init__.py
qtbox/demo/lineedit/func/__init__.py
qtbox/demo/lineedit/func/demo1.py
qtbox/demo/lineedit/func/demo2.py
qtbox/demo/lineedit/func/demo3.py
qtbox/demo/lineedit/func/demo4.py
qtbox/demo/lineedit/func/demo5.py
qtbox/demo/lineedit/style/__init__.py
qtbox/demo/lineedit/style/demo1.py
qtbox-1.2.0.dist-info/METADATA
qtbox-1.2.0.dist-info/WHEEL
qtbox-1.2.0.dist-info/entry_points.txt
qtbox-1.2.0.dist-info/licenses/LICENSE
qtbox-1.2.0.dist-info/RECORD
