Metadata-Version: 2.1
Name: qtbox
Version: 1.2.0
Summary: Find your target PyQt or PySide widget here.
Project-URL: Homepage, https://github.com/la-vie-est-belle/qtbox
Author-email: Louis Ren <louasure@126.com>
License-File: LICENSE
Classifier: License :: OSI Approved :: GNU General Public License v3 (GPLv3)
Classifier: Operating System :: OS Independent
Classifier: Programming Language :: Python :: 3
Requires-Python: >=3.7
Requires-Dist: pygments
Requires-Dist: pyqt5
